Workbook

Sheet Backlog
A1: ID | B1: Sprint | C1: Sprint Focus | D1: Start | E1: Due | F1: Title | G1: Area | H1: Type | I1: Priority | J1: Est. (h) | K1: Files / Path | L1: Acceptance criteria | M1: Status | N1: Owner | O1: Notes
A2: 1 | B2: Sprint 1 | C2: Security & auth hardening | D2: 46055 | E2: 46056 | F2: Return after 'User already exists' in createUser | G2: Auth | H2: Bug | I2: Critical | J2: 1 | K2: backend/controllers/userController.js | L2: Registering with an existing email returns a single 400 JSON response, no user is saved, and no 'Cannot set headers after they are sent' error appears in the log. | M2: Not started
A3: 2 | B3: Sprint 1 | C3: Security & auth hardening | D3: 46055 | E3: 46056 | F3: Send 401 on failed login instead of hanging | G3: Auth | H3: Bug | I3: Critical | J3: 1 | K3: backend/controllers/userController.js | L3: Unknown email or wrong password returns 401 {message:'Invalid email or password'}; the request never hangs open. | M3: Not started
A4: 3 | B4: Sprint 1 | C4: Security & auth hardening | D4: 46055 | E4: 46057 | F4: Remove console.log of email and plaintext password | G4: Security | H4: Bug | I4: Critical | J4: 0.5 | K4: backend/controllers/userController.js | L4: No credential values appear in server logs for any auth request. | M4: Not started
A5: 4 | B5: Sprint 1 | C5: Security & auth hardening | D5: 46055 | E5: 46057 | F5: Fix 'httyOnly' typo in logout cookie options | G5: Auth | H5: Bug | I5: High | J5: 0.5 | K5: backend/controllers/userController.js | L5: Logout clears the jwt cookie with correct httpOnly flag; a follow-up /profile call returns 401. | M5: Not started
A6: 5 | B6: Sprint 1 | C6: Security & auth hardening | D6: 46055 | E6: 46058 | F6: Strip password hashes from GET /api/users response | G6: Security | H6: Bug | I6: High | J6: 0.5 | K6: backend/controllers/userController.js | L6: getAllUsers uses .select('-password'); no hash field is present in the admin user list payload. | M6: Not started
A7: 6 | B7: Sprint 1 | C7: Security & auth hardening | D7: 46055 | E7: 46058 | F7: Add global errorHandler and notFound middleware | G7: Backend | H7: Chore | I7: High | J7: 3 | K7: backend/middlewares/, backend/index.js | L7: Unmatched routes return 404 JSON; thrown errors return the intended status code with a stack trace only in development. | M7: Not started
A8: 7 | B8: Sprint 1 | C8: Security & auth hardening | D8: 46055 | E8: 46059 | F8: Rewrite asyncHandler to forward errors instead of always 500 | G8: Backend | H8: Bug | I8: High | J8: 1.5 | K8: backend/middlewares/asyncHandler.js | L8: A controller that sets res.status(404) before throwing responds 404, not 500. | M8: Not started
A9: 8 | B9: Sprint 1 | C9: Security & auth hardening | D9: 46055 | E9: 46059 | F9: Fix checkId to call next(error) for invalid ObjectId | G9: Backend | H9: Bug | I9: Medium | J9: 1 | K9: backend/middlewares/checkId.js | L9: GET /api/products/abc returns a clean 404 JSON instead of an unhandled synchronous throw. | M9: Not started
A10: 9 | B10: Sprint 1 | C10: Security & auth hardening | D10: 46055 | E10: 46062 | F10: Validate required env vars at boot and fail fast | G10: Backend | H10: Chore | I10: High | J10: 1.5 | K10: backend/index.js, backend/config/db.js | L10: Missing MONGO_URI or JWT_SECRET exits with a named error before the server starts listening. | M10: Not started
A11: 10 | B11: Sprint 1 | C11: Security & auth hardening | D11: 46055 | E11: 46062 | F11: Fix cookie secure flag so local HTTP login works | G11: Auth | H11: Bug | I11: High | J11: 1 | K11: backend/utils/createToken.js | L11: Cookie is secure only when NODE_ENV==='production'; login works over http://localhost and stays secure in production. | M11: Not started
A12: 11 | B12: Sprint 1 | C12: Security & auth hardening | D12: 46055 | E12: 46063 | F12: Rate limit login and registration endpoints | G12: Security | H12: Feature | I12: High | J12: 2 | K12: backend/routes/userRoutes.js | L12: express-rate-limit caps /api/users/auth at 5 attempts per 15 min per IP and returns 429 with a retry hint. | M12: Not started
A13: 12 | B13: Sprint 1 | C13: Security & auth hardening | D13: 46055 | E13: 46063 | F13: Add helmet and a configured CORS allowlist | G13: Security | H13: Feature | I13: High | J13: 2 | K13: backend/index.js | L13: helmet is enabled and CORS accepts credentials only from origins in the CLIENT_URL allowlist. | M13: Not started
... A101: 100 | B101: Sprint 6 | C101: Testing, CI/CD & deployment | D101: 46125 | E101: 46142 | F101: Add structured logging and a health check endpoint | G101: DevOps | H101: Feature | I101: Medium | J101: 3 | K101: backend/index.js, backend/utils/logger.js | L101: pino logs requests with a request id and GET /api/health reports uptime plus database connectivity. | M101: Not started

Sheet Sprint Plan
A1: Sprint plan - Feb 2 to Apr 30, 2026
A2: Every figure below is a live formula over the Backlog sheet.
A4: Sprint | B4: Focus | C4: Start | D4: End | E4: Tasks | F4: Est. (h) | G4: Critical | H4: High | I4: Done | J4: % Done
A5: Sprint 1 | B5: Security & auth hardening | C5: 46055 | D5: 46066 | E5: =COUNTIF(Backlog!$B$2:$B$101,$A5) -> 17 | F5: =SUMIF(Backlog!$B$2:$B$101,$A5,Backlog!$J$2:$J$101) -> 30.5 | G5: =COUNTIFS(Backlog!$B$2:$B$101,$A5,Backlog!$I$2:$I$101,"Critical") -> 3 | H5: =COUNTIFS(Backlog!$B$2:$B$101,$A5,Backlog!$I$2:$I$101,"High") -> 9 | I5: =COUNTIFS(Backlog!$B$2:$B$101,$A5,Backlog!$M$2:$M$101,"Done") -> 0 | J5: =IFERROR($I5/$E5,0) -> 0
A6: Sprint 2 | B6: Products, categories & uploads | C6: 46069 | D6: 46080 | E6: =COUNTIF(Backlog!$B$2:$B$101,$A6) -> 20 | F6: =SUMIF(Backlog!$B$2:$B$101,$A6,Backlog!$J$2:$J$101) -> 45 | G6: =COUNTIFS(Backlog!$B$2:$B$101,$A6,Backlog!$I$2:$I$101,"Critical") -> 1 | H6: =COUNTIFS(Backlog!$B$2:$B$101,$A6,Backlog!$I$2:$I$101,"High") -> 8 | I6: =COUNTIFS(Backlog!$B$2:$B$101,$A6,Backlog!$M$2:$M$101,"Done") -> 0 | J6: =IFERROR($I6/$E6,0) -> 0
A7: Sprint 3 | B7: Orders, payments & data integrity | C7: 46083 | D7: 46094 | E7: =COUNTIF(Backlog!$B$2:$B$101,$A7) -> 18 | F7: =SUMIF(Backlog!$B$2:$B$101,$A7,Backlog!$J$2:$J$101) -> 64 | G7: =COUNTIFS(Backlog!$B$2:$B$101,$A7,Backlog!$I$2:$I$101,"Critical") -> 5 | H7: =COUNTIFS(Backlog!$B$2:$B$101,$A7,Backlog!$I$2:$I$101,"High") -> 5 | I7: =COUNTIFS(Backlog!$B$2:$B$101,$A7,Backlog!$M$2:$M$101,"Done") -> 0 | J7: =IFERROR($I7/$E7,0) -> 0
A8: Sprint 4 | B8: Frontend state & checkout | C8: 46097 | D8: 46108 | E8: =COUNTIF(Backlog!$B$2:$B$101,$A8) -> 17 | F8: =SUMIF(Backlog!$B$2:$B$101,$A8,Backlog!$J$2:$J$101) -> 36 | G8: =COUNTIFS(Backlog!$B$2:$B$101,$A8,Backlog!$I$2:$I$101,"Critical") -> 0 | H8: =COUNTIFS(Backlog!$B$2:$B$101,$A8,Backlog!$I$2:$I$101,"High") -> 5 | I8: =COUNTIFS(Backlog!$B$2:$B$101,$A8,Backlog!$M$2:$M$101,"Done") -> 0 | J8: =IFERROR($I8/$E8,0) -> 0
A9: Sprint 5 | B9: UX, performance & accessibility | C9: 46111 | D9: 46122 | E9: =COUNTIF(Backlog!$B$2:$B$101,$A9) -> 16 | F9: =SUMIF(Backlog!$B$2:$B$101,$A9,Backlog!$J$2:$J$101) -> 54 | G9: =COUNTIFS(Backlog!$B$2:$B$101,$A9,Backlog!$I$2:$I$101,"Critical") -> 0 | H9: =COUNTIFS(Backlog!$B$2:$B$101,$A9,Backlog!$I$2:$I$101,"High") -> 4 | I9: =COUNTIFS(Backlog!$B$2:$B$101,$A9,Backlog!$M$2:$M$101,"Done") -> 0 | J9: =IFERROR($I9/$E9,0) -> 0
A10: Sprint 6 | B10: Testing, CI/CD & deployment | C10: 46125 | D10: 46142 | E10: =COUNTIF(Backlog!$B$2:$B$101,$A10) -> 12 | F10: =SUMIF(Backlog!$B$2:$B$101,$A10,Backlog!$J$2:$J$101) -> 47 | G10: =COUNTIFS(Backlog!$B$2:$B$101,$A10,Backlog!$I$2:$I$101,"Critical") -> 0 | H10: =COUNTIFS(Backlog!$B$2:$B$101,$A10,Backlog!$I$2:$I$101,"High") -> 7 | I10: =COUNTIFS(Backlog!$B$2:$B$101,$A10,Backlog!$M$2:$M$101,"Done") -> 0 | J10: =IFERROR($I10/$E10,0) -> 0
A11: TOTAL | B11: Full Feb-Apr backlog | C11: 46055 | D11: 46142 | E11: =SUM(E5:E10) -> 100 | F11: =SUM(F5:F10) -> 276.5 | G11: =SUM(G5:G10) -> 9 | H11: =SUM(H5:H10) -> 38 | I11: =SUM(I5:I10) -> 0 | J11: =IFERROR($I11/$E11,0) -> 0
A14: Breakdown by area
A15: Area | B15: Tasks | C15: Est. (h) | D15: Share of hours
A16: Accessibility | B16: =COUNTIF(Backlog!$G$2:$G$101,$A16) -> 3 | C16: =SUMIF(Backlog!$G$2:$G$101,$A16,Backlog!$J$2:$J$101) -> 8 | D16: =IFERROR($C16/SUM($C$16:$C$28),0) -> 0.028933092
A17: Auth | B17: =COUNTIF(Backlog!$G$2:$G$101,$A17) -> 6 | C17: =SUMIF(Backlog!$G$2:$G$101,$A17,Backlog!$J$2:$J$101) -> 11.5 | D17: =IFERROR($C17/SUM($C$16:$C$28),0) -> 0.04159132
A18: Backend | B18: =COUNTIF(Backlog!$G$2:$G$101,$A18) -> 29 | C18: =SUMIF(Backlog!$G$2:$G$101,$A18,Backlog!$J$2:$J$101) -> 63 | D18: =IFERROR($C18/SUM($C$16:$C$28),0) -> 0.2278481
A19: Chore | B19: =COUNTIF(Backlog!$G$2:$G$101,$A19) -> 2 | C19: =SUMIF(Backlog!$G$2:$G$101,$A19,Backlog!$J$2:$J$101) -> 2.5 | D19: =IFERROR($C19/SUM($C$16:$C$28),0) -> 0.0090415913
A20: DevOps | B20: =COUNTIF(Backlog!$G$2:$G$101,$A20) -> 8 | C20: =SUMIF(Backlog!$G$2:$G$101,$A20,Backlog!$J$2:$J$101) -> 22 | D20: =IFERROR($C20/SUM($C$16:$C$28),0) -> 0.079566004
A21: Docs | B21: =COUNTIF(Backlog!$G$2:$G$101,$A21) -> 1 | C21: =SUMIF(Backlog!$G$2:$G$101,$A21,Backlog!$J$2:$J$101) -> 4 | D21: =IFERROR($C21/SUM($C$16:$C$28),0) -> 0.014466546
A22: Feature | B22: =COUNTIF(Backlog!$G$2:$G$101,$A22) -> 12 | C22: =SUMIF(Backlog!$G$2:$G$101,$A22,Backlog!$J$2:$J$101) -> 57 | D22: =IFERROR($C22/SUM($C$16:$C$28),0) -> 0.20614828
A23: Frontend | B23: =COUNTIF(Backlog!$G$2:$G$101,$A23) -> 15 | C23: =SUMIF(Backlog!$G$2:$G$101,$A23,Backlog!$J$2:$J$101) -> 34.5 | D23: =IFERROR($C23/SUM($C$16:$C$28),0) -> 0.12477396
A24: Payments | B24: =COUNTIF(Backlog!$G$2:$G$101,$A24) -> 3 | C24: =SUMIF(Backlog!$G$2:$G$101,$A24,Backlog!$J$2:$J$101) -> 18 | D24: =IFERROR($C24/SUM($C$16:$C$28),0) -> 0.065099458
A25: Performance | B25: =COUNTIF(Backlog!$G$2:$G$101,$A25) -> 3 | C25: =SUMIF(Backlog!$G$2:$G$101,$A25,Backlog!$J$2:$J$101) -> 8 | D25: =IFERROR($C25/SUM($C$16:$C$28),0) -> 0.028933092
A26: SEO | B26: =COUNTIF(Backlog!$G$2:$G$101,$A26) -> 3 | C26: =SUMIF(Backlog!$G$2:$G$101,$A26,Backlog!$J$2:$J$101) -> 8 | D26: =IFERROR($C26/SUM($C$16:$C$28),0) -> 0.028933092
A27: Security | B27: =COUNTIF(Backlog!$G$2:$G$101,$A27) -> 9 | C27: =SUMIF(Backlog!$G$2:$G$101,$A27,Backlog!$J$2:$J$101) -> 13 | D27: =IFERROR($C27/SUM($C$16:$C$28),0) -> 0.047016275
A28: Testing | B28: =COUNTIF(Backlog!$G$2:$G$101,$A28) -> 6 | C28: =SUMIF(Backlog!$G$2:$G$101,$A28,Backlog!$J$2:$J$101) -> 27 | D28: =IFERROR($C28/SUM($C$16:$C$28),0) -> 0.097649186

Sheet How to use
A1: How to use this backlog
A2: Backlog for | B2: github.com/Azizbeccoder/E-commerce-web_site (MERN e-commerce: Express + MongoDB API, React + Redux Toolkit + Vite frontend)
A3: Window | B3: February 2 - April 30, 2026, split into six two-week sprints.
A4: How it was built | B4: Every item was written against the actual code in the repo. Bug items name a real defect found in a specific file; feature and chore items build on what already exists.
A6: Columns you edit | B6: Status, Owner, Notes. Everything else is reference.
A7: Status values | B7: Not started / In progress / In review / Blocked / Done (dropdown)
A8: Priority values | B8: Critical / High / Medium / Low (dropdown; Critical and High are colour-coded)
A9: Est. (h) | B9: Rough solo-developer estimate in hours. Adjust freely - the Sprint Plan totals recalculate.
A10: Sprint Plan tab | B10: Live COUNTIF/SUMIF formulas over the Backlog sheet. Change a Status to Done and the % Done column updates.
A12: Example row | B12: Row 2: ID 1, Sprint 1, due 2026-02-02, 'Return after User already exists in createUser', Auth / Bug / Critical, 1.0h - set Status to 'In progress' and put your name in Owner.
A14: Assumptions | B14: Estimates assume one full-time developer and no team velocity data was available - they are the author's judgement, not measured. Due dates are spread evenly across each sprint's business days rather than dependency-ordered.
A15: Sprint 1 rationale | B15: Auth and error-handling defects come first because several of them (missing return on duplicate signup, silent hang on failed login, plaintext password logging) affect every request path underneath.
A16: Sprint 3 rationale | B16: Payment verification and stock decrement are grouped because both are order-write concerns and touch the same controller.
